[{"username":"redleafnew","contributions":1241,"avatar":"https://avatars.githubusercontent.com/u/22135631?v=4"},{"username":"northword","contributions":732,"avatar":"https://avatars.githubusercontent.com/u/44738481?v=4"},{"username":"zepinglee","contributions":671,"avatar":"https://avatars.githubusercontent.com/u/12290822?v=4"},{"username":"Chikit-L","contributions":34,"avatar":"https://avatars.githubusercontent.com/u/57130625?v=4"},{"username":"ZMAlt","contributions":32,"avatar":"https://avatars.githubusercontent.com/u/35285040?v=4"},{"username":"Helloxiaolaodi","contributions":20,"avatar":"https://avatars.githubusercontent.com/u/118160321?v=4"},{"username":"syt2","contributions":20,"avatar":"https://avatars.githubusercontent.com/u/15265829?v=4"},{"username":"volatile-static","contributions":20,"avatar":"https://avatars.githubusercontent.com/u/59945270?v=4"},{"username":"thebetter2","contributions":17,"avatar":"https://avatars.githubusercontent.com/u/122372181?v=4"},{"username":"l0o0","contributions":15,"avatar":"https://avatars.githubusercontent.com/u/2743744?v=4"},{"username":"RisenL","contributions":11,"avatar":"https://avatars.githubusercontent.com/u/79988120?v=4"},{"username":"pencilheart","contributions":7,"avatar":"https://avatars.githubusercontent.com/u/61617063?v=4"},{"username":"jiaojiaodubai","contributions":5,"avatar":"https://avatars.githubusercontent.com/u/63148861?v=4"},{"username":"Maschinist-LZY","contributions":4,"avatar":"https://avatars.githubusercontent.com/u/46670284?v=4"},{"username":"shandianchengzi","contributions":3,"avatar":"https://avatars.githubusercontent.com/u/58585665?v=4"},{"username":"wakewon","contributions":3,"avatar":"https://avatars.githubusercontent.com/u/40191996?v=4"},{"username":"guohui-ma","contributions":2,"avatar":"https://avatars.githubusercontent.com/u/11820036?v=4"},{"username":"jiayoudangdang","contributions":2,"avatar":"https://avatars.githubusercontent.com/u/32636666?v=4"},{"username":"longavailable","contributions":2,"avatar":"https://avatars.githubusercontent.com/u/24582280?v=4"},{"username":"Maple-YZ","contributions":2,"avatar":"https://avatars.githubusercontent.com/u/61239030?v=4"},{"username":"panhaoyu","contributions":2,"avatar":"https://avatars.githubusercontent.com/u/23495987?v=4"},{"username":"mbs0221","contributions":2,"avatar":"https://avatars.githubusercontent.com/u/12655889?v=4"},{"username":"ChenglongMa","contributions":2,"avatar":"https://avatars.githubusercontent.com/u/33501679?v=4"},{"username":"ShawnPi233","contributions":1,"avatar":"https://avatars.githubusercontent.com/u/84508049?v=4"},{"username":"BBlakeana","contributions":1,"avatar":"https://avatars.githubusercontent.com/u/20284371?v=4"},{"username":"Enceladus6","contributions":1,"avatar":"https://avatars.githubusercontent.com/u/51427409?v=4"},{"username":"JaredHHu","contributions":1,"avatar":"https://avatars.githubusercontent.com/u/93370202?v=4"},{"username":"lincolnelectric","contributions":1,"avatar":"https://avatars.githubusercontent.com/u/30498748?v=4"},{"username":"aoaim","contributions":1,"avatar":"https://avatars.githubusercontent.com/u/48897696?v=4"},{"username":"SuperOwenX","contributions":1,"avatar":"https://avatars.githubusercontent.com/u/37410613?v=4"},{"username":"chengda1229","contributions":1,"avatar":"https://avatars.githubusercontent.com/u/83005065?v=4"},{"username":"wrlssqi","contributions":1,"avatar":"https://avatars.githubusercontent.com/u/9946624?v=4"},{"username":"xjtusjtu","contributions":1,"avatar":"https://avatars.githubusercontent.com/u/57665402?v=4"},{"username":"Comte0825","contributions":1,"avatar":"https://avatars.githubusercontent.com/u/113301080?v=4"},{"username":"rujinlong","contributions":1,"avatar":"https://avatars.githubusercontent.com/u/2161381?v=4"},{"username":"MoYuXianR","contributions":1,"avatar":"https://avatars.githubusercontent.com/u/151877887?v=4"},{"username":"Morimiue","contributions":1,"avatar":"https://avatars.githubusercontent.com/u/41257880?v=4"},{"username":"Maverick618","contributions":1,"avatar":"https://avatars.githubusercontent.com/u/61676133?v=4"},{"username":"windingwind","contributions":1,"avatar":"https://avatars.githubusercontent.com/u/33902321?v=4"},{"username":"zzlb0224","contributions":1,"avatar":"https://avatars.githubusercontent.com/u/8912444?v=4"},{"username":"q77190858","contributions":1,"avatar":"https://avatars.githubusercontent.com/u/10094838?v=4"},{"username":"fkguo","contributions":1,"avatar":"https://avatars.githubusercontent.com/u/62633089?v=4"},{"username":"ci-ke","contributions":1,"avatar":"https://avatars.githubusercontent.com/u/14360436?v=4"},{"username":"TimeTrapzz","contributions":1,"avatar":"https://avatars.githubusercontent.com/u/55572425?v=4"},{"username":"MuiseDestiny","contributions":1,"avatar":"https://avatars.githubusercontent.com/u/51939531?v=4"},{"username":"etShaw-zh","contributions":1,"avatar":"https://avatars.githubusercontent.com/u/63627218?v=4"},{"username":"Creling","contributions":1,"avatar":"https://avatars.githubusercontent.com/u/43109504?v=4"},{"username":"bact","contributions":1,"avatar":"https://avatars.githubusercontent.com/u/128572?v=4"}]